trapit/README.md
trapit/__init__.py
trapit/trapit.py
trapit/examples/Run-Examples.bat
trapit/examples/Run-Examples.err
trapit/examples/Run-Examples.out
trapit/examples/Run-Examples.ps1
trapit/examples/Test-Examples.bat
trapit/examples/Test-Examples.err
trapit/examples/Test-Examples.out
trapit/examples/Test-Examples.ps1
trapit/examples/test-colgroup.log
trapit/examples/test-helloworld.log
trapit/examples/colgroup/Format-JSON-ColGroup.bat
trapit/examples/colgroup/Format-JSON-ColGroup.err
trapit/examples/colgroup/Format-JSON-ColGroup.out
trapit/examples/colgroup/Format-JSON-ColGroup.ps1
trapit/examples/colgroup/Run-Colgroup.err
trapit/examples/colgroup/Run-Colgroup.out
trapit/examples/colgroup/colgroup.json
trapit/examples/colgroup/colgroup.ps1
trapit/examples/colgroup/colgroup.py
trapit/examples/colgroup/colgroup_inp.csv
trapit/examples/colgroup/colgroup_out.csv
trapit/examples/colgroup/colgroup_out.json
trapit/examples/colgroup/colgroup_sce.csv
trapit/examples/colgroup/colgroup_temp.json
trapit/examples/colgroup/fantasy_premier_league_player_stats.csv
trapit/examples/colgroup/fantasy_premier_league_player_stats.csv.log
trapit/examples/colgroup/maincolgroup.py
trapit/examples/colgroup/testcolgroup.py
trapit/examples/colgroup/utils_cg.py
trapit/examples/colgroup/__pycache__/colgroup.cpython-313.pyc
trapit/examples/colgroup/__pycache__/colgroup.cpython-39.pyc
trapit/examples/colgroup/__pycache__/utils_cg.cpython-313.pyc
trapit/examples/colgroup/__pycache__/utils_cg.cpython-39.pyc
trapit/examples/colgroup/colgroup---python/actual_expected-mismatch.html
trapit/examples/colgroup/colgroup---python/colgroup---python.html
trapit/examples/colgroup/colgroup---python/colgroup---python.txt
trapit/examples/colgroup/colgroup---python/log-file-does-not-exist-at-time-of-call.html
trapit/examples/colgroup/colgroup---python/log-file-exists-at-time-of-call.html
trapit/examples/colgroup/colgroup---python/long-key.html
trapit-1.2.1.dist-info/METADATA
trapit-1.2.1.dist-info/WHEEL
trapit-1.2.1.dist-info/top_level.txt
trapit-1.2.1.dist-info/RECORD
