Metadata-Version: 2.4
Name: trapit
Version: 1.2.1
Summary: Trapit python utility for Math Function Unit Test design pattern
Home-page: https://github.com/brenpatf/trapit_python_tester
Author: Brendan Furey
Author-email: brenpatf@gmail.com
Classifier: Programming Language :: Python :: 3
Classifier: License :: OSI Approved :: MIT License
Classifier: Operating System :: OS Independent
Dynamic: author
Dynamic: author-email
Dynamic: classifier
Dynamic: description
Dynamic: description-content-type
Dynamic: home-page
Dynamic: summary
